LICENSE.txt
README.md
setup.cfg
setup.py
Classes/Accessee.py
Classes/Accessor.py
Classes/Accessor2Accessee.py
Classes/Attribute.py
Classes/Base.py
Classes/Class.py
Classes/Constant.py
Classes/Depends.py
Classes/Enum.py
Classes/Flow.py
Classes/Generic.py
Classes/Group.py
Classes/Instance.py
Classes/List.py
Classes/Method.py
Classes/Package.py
Classes/Parameter.py
Classes/Permission.py
Classes/Returns.py
Classes/Set.py
Classes/Type.py
Classes/User.py
Classes/User2Group.py
Classes/Version.py
Classes/Visualisation.py
Classes/__init__.py
ClassyData.egg-info/PKG-INFO
ClassyData.egg-info/SOURCES.txt
ClassyData.egg-info/dependency_links.txt
ClassyData.egg-info/requires.txt
ClassyData.egg-info/top_level.txt
Handlers/Crown.py
Handlers/Jester.py
Handlers/__init__.py
bin/TopHat.py