Metadata-Version: 2.4
Name: ClassyData
Version: 1.51
Home-page: https://github.com/eddo888/ClassyData
Download-URL: https://github.com/eddo888/ClassyData/archive/1.51.tar.gz
Author: David Edson
Author-email: eddo888@tpg.com.au
License: MIT
License-File: LICENSE.txt
Requires-Dist: mysql-connector-python
Requires-Dist: sqlalchemy
Requires-Dist: sqlalchemy-utils
Requires-Dist: faker
Requires-Dist: jsonweb
Requires-Dist: Baubles
Requires-Dist: Perdy
Requires-Dist: Argumental
Requires-Dist: Spanners
Requires-Dist: GoldenChild
Dynamic: author
Dynamic: author-email
Dynamic: description
Dynamic: description-content-type
Dynamic: download-url
Dynamic: home-page
Dynamic: license
Dynamic: license-file
Dynamic: requires-dist
